sqlify/__init__.py
sqlify/builder.py
sqlify/cli.py
sqlify/exceptions.py
sqlify/migrations.py
sqlify/operators.py
sqlify/session.py
sqlify/value_objects.py
sqlify-0.7.4.dist-info/LICENSE
sqlify-0.7.4.dist-info/WHEEL
sqlify-0.7.4.dist-info/METADATA
sqlify-0.7.4.dist-info/RECORD
